lucastamatescu/__init__.py
lucastamatescu/overlay.py
lucastamatescu/rtspstreaming.py
lucastamatescu-0.3.1.dist-info/DESCRIPTION.rst
lucastamatescu-0.3.1.dist-info/METADATA
lucastamatescu-0.3.1.dist-info/RECORD
lucastamatescu-0.3.1.dist-info/WHEEL
lucastamatescu-0.3.1.dist-info/metadata.json
lucastamatescu-0.3.1.dist-info/top_level.txt
