Metadata-Version: 2.0
Name: lucastamatescu
Version: 0.3.1
Summary: A collection of utilities created by Luca for various projects
Home-page: https://github.com/luca-stamatescu/lucastamatescu-python-package
Author: Luca Stamatescu
Author-email: developer@lucastamatescu.com
License: UNKNOWN
Keywords: pip,luca,stamatescu
Platform: UNKNOWN
